{
  "id": 135,
  "name": "Suniel Kumar",
  "username": "sunielkumar",
  "avatar_template": "/letter_avatar_proxy/v2/letter/s/f08c70/{size}.png",
  "created_at": "2015-06-13T05:56:17.000Z",
  "cooked": "<p>When some indiviual or organization is open and clear that they want to leverage \u2018open source\u2019 for commercial business interests, it should be absolutely okay to charge fees to facilitate self-certification.</p>\n<p>There must be No Certification Fees but there should be means of charging fees for facilitating certification.</p>\n<p>There must be No certifying authority - but should be enablers of self certification . Care should be taken that in no way such fees/ process should differentiate hobbyists, DIYers or students works.</p>",
  "post_number": 8,
  "post_type": 1,
  "updated_at": "2017-02-14T04:29:17.472Z",
  "reply_count": 0,
  "reply_to_post_number": null,
  "quote_count": 0,
  "avg_time": 11,
  "incoming_link_count": 0,
  "reads": 2,
  "score": 0.95,
  "yours": false,
  "topic_id": 42,
  "topic_slug": "6-should-certification-require-fees",
  "display_username": "Suniel Kumar",
  "primary_group_name": null,
  "primary_group_flair_url": null,
  "primary_group_flair_bg_color": null,
  "primary_group_flair_color": null,
  "version": 1,
  "can_edit": false,
  "can_delete": false,
  "can_recover": false,
  "can_wiki": false,
  "user_title": null,
  "raw": "When some indiviual or organization is open and clear that they want to leverage 'open source' for commercial business interests, it should be absolutely okay to charge fees to facilitate self-certification.\n\nThere must be No Certification Fees but there should be means of charging fees for facilitating certification.\n\nThere must be No certifying authority - but should be enablers of self certification . Care should be taken that in no way such fees/ process should differentiate hobbyists, DIYers or students works.",
  "actions_summary": [],
  "moderator": false,
  "admin": false,
  "staff": false,
  "user_id": 708,
  "hidden": false,
  "trust_level": 1,
  "deleted_at": null,
  "user_deleted": false,
  "edit_reason": null,
  "can_view_edit_history": true,
  "wiki": false
}