{
  "id": 580,
  "name": "Wayne Seltzer",
  "username": "wseltzer",
  "avatar_template": "/user_avatar/community.oshwa.org/wseltzer/{size}/65_1.png",
  "created_at": "2018-09-17T19:02:10.972Z",
  "cooked": "<p><div class=\"lightbox-wrapper\"><a class=\"lightbox\" href=\"//community.oshwa.org/uploads/default/original/1X/df94d9ea2c89ca0ed8a96ba32f911e5b4db9be07.jpg\" data-download-href=\"//community.oshwa.org/uploads/default/df94d9ea2c89ca0ed8a96ba32f911e5b4db9be07\" title=\"alumni-people.jpg\"><img src=\"//community.oshwa.org/uploads/default/optimized/1X/df94d9ea2c89ca0ed8a96ba32f911e5b4db9be07_1_690x345.jpg\" width=\"690\" height=\"345\"><div class=\"meta\">\n<span class=\"filename\">alumni-people.jpg</span><span class=\"informations\">720x360 37.1 KB</span><span class=\"expand\"></span>\n</div></a></div></p>",
  "post_number": 5,
  "post_type": 1,
  "updated_at": "2018-09-17T19:07:16.847Z",
  "reply_count": 0,
  "reply_to_post_number": 4,
  "quote_count": 0,
  "avg_time": 26,
  "incoming_link_count": 1,
  "reads": 8,
  "score": 7.9,
  "yours": false,
  "topic_id": 205,
  "topic_slug": "ohs-2018-boston-events-thread",
  "display_username": "Wayne Seltzer",
  "primary_group_name": null,
  "primary_group_flair_url": null,
  "primary_group_flair_bg_color": null,
  "primary_group_flair_color": null,
  "version": 2,
  "can_edit": false,
  "can_delete": false,
  "can_recover": false,
  "can_wiki": false,
  "user_title": null,
  "reply_to_user": {
    "username": "wseltzer",
    "avatar_template": "/user_avatar/community.oshwa.org/wseltzer/{size}/65_1.png"
  },
  "raw": "<img src='/uploads/default/original/1X/df94d9ea2c89ca0ed8a96ba32f911e5b4db9be07.jpg'>",
  "actions_summary": [],
  "moderator": false,
  "admin": false,
  "staff": false,
  "user_id": 1109,
  "hidden": false,
  "trust_level": 0,
  "deleted_at": null,
  "user_deleted": false,
  "edit_reason": "downloaded local copies of images",
  "can_view_edit_history": true,
  "wiki": false
}