{
  "id": 756,
  "name": "jgriessen",
  "username": "jgriessen",
  "avatar_template": "/user_avatar/community.oshwa.org/jgriessen/{size}/33_1.png",
  "created_at": "2019-08-30T00:11:32.938Z",
  "cooked": "<p>As I understand it the OSHW license is based on copyright, so if you make a derivative and different PCB design, it will not affect your pcb\u2019s status as OSHW certified.  In the other direction,<br>\nOSHW has no teeth that I remember for stopping your use of your design.  You are the originator, not a licensee, so you have origin rights to license it two ways or 3 or 4 ways\u2026etc.</p>",
  "post_number": 2,
  "post_type": 1,
  "updated_at": "2019-08-30T00:11:32.938Z",
  "reply_count": 1,
  "reply_to_post_number": null,
  "quote_count": 0,
  "avg_time": 33,
  "incoming_link_count": 0,
  "reads": 5,
  "score": 7.65,
  "yours": false,
  "topic_id": 474,
  "topic_slug": "releasing-oshw-alongside-non-oshw-version",
  "display_username": "jgriessen",
  "primary_group_name": null,
  "primary_group_flair_url": null,
  "primary_group_flair_bg_color": null,
  "primary_group_flair_color": null,
  "version": 1,
  "can_edit": false,
  "can_delete": false,
  "can_recover": false,
  "can_wiki": false,
  "user_title": null,
  "raw": "As I understand it the OSHW license is based on copyright, so if you make a derivative and different PCB design, it will not affect your pcb's status as OSHW certified.  In the other direction,\nOSHW has no teeth that I remember for stopping your use of your design.  You are the originator, not a licensee, so you have origin rights to license it two ways or 3 or 4 ways...etc.",
  "actions_summary": [],
  "moderator": false,
  "admin": false,
  "staff": false,
  "user_id": 756,
  "hidden": false,
  "trust_level": 1,
  "deleted_at": null,
  "user_deleted": false,
  "edit_reason": null,
  "can_view_edit_history": true,
  "wiki": false
}